bcs_oi_api/__init__.py
bcs_oi_api/bcs_oi_api.py
bcs_oi_api/models/__init__.py
bcs_oi_api/models/models.py
bcs_oi_api/models/bulk/__init__.py
bcs_oi_api/models/bulk/models.py
bcs_oi_api/models/collectors/__init__.py
bcs_oi_api/models/collectors/models.py
bcs_oi_api/models/config_best_practice/__init__.py
bcs_oi_api/models/config_best_practice/models.py
bcs_oi_api/models/contracts/__init__.py
bcs_oi_api/models/contracts/models.py
bcs_oi_api/models/device_groups/__init__.py
bcs_oi_api/models/device_groups/models.py
bcs_oi_api/models/device_reset/__init__.py
bcs_oi_api/models/device_reset/models.py
bcs_oi_api/models/inventory/__init__.py
bcs_oi_api/models/inventory/models.py
bcs_oi_api/models/place_in_network/__init__.py
bcs_oi_api/models/place_in_network/models.py
bcs_oi_api/models/product_alerts/__init__.py
bcs_oi_api/models/product_alerts/models.py
bcs_oi_api/models/risk_mitigation/__init__.py
bcs_oi_api/models/risk_mitigation/models.py
bcs_oi_api/models/software_track/__init__.py
bcs_oi_api/models/software_track/models.py
bcs_oi_api/models/syslog/__init__.py
bcs_oi_api/models/syslog/models.py
bcs_oi_api/models/unidentified_inventory/__init__.py
bcs_oi_api/models/unidentified_inventory/models.py
bcs_oi_api-1.1.1.dist-info/LICENSE.md
bcs_oi_api-1.1.1.dist-info/METADATA
bcs_oi_api-1.1.1.dist-info/WHEEL
bcs_oi_api-1.1.1.dist-info/top_level.txt
bcs_oi_api-1.1.1.dist-info/RECORD
