Metadata-Version: 2.1
Name: bcs-oi-api
Version: 1.1.1
Summary: Business Critical Services Operational Insights API SDK
Home-page: https://github.com/CiscoDevNet/bcs-oi-api-sdk
Author: Kristof Van Coillie
Author-email: kvancoil@cisco.com
Project-URL: Bug Tracker, https://github.com/CiscoDevNet/bcs-oi-api-sdk/issues
Classifier: Development Status :: 4 - Beta
Classifier: Intended Audience :: Developers
Classifier: Intended Audience :: System Administrators
Classifier: Intended Audience :: Telecommunications Industry
Classifier: Natural Language :: English
Classifier: License :: OSI Approved :: MIT License
Classifier: Programming Language :: Python :: 3
Classifier: Programming Language :: Python :: 3.7
Classifier: Programming Language :: Python :: 3.8
Classifier: Programming Language :: Python :: 3.9
Classifier: Operating System :: OS Independent
Classifier: Topic :: System :: Networking :: Monitoring
Classifier: Topic :: System :: Monitoring
Requires-Python: >=3.7
License-File: LICENSE.md
Requires-Dist: jsonlines
Requires-Dist: requests
Requires-Dist: pyjwt
Requires-Dist: pydantic
